byted_lighten_validator/__init__.py
byted_lighten_validator-0.0.1.dist-info/METADATA
byted_lighten_validator-0.0.1.dist-info/WHEEL
byted_lighten_validator-0.0.1.dist-info/top_level.txt
byted_lighten_validator-0.0.1.dist-info/RECORD
